zpp_args/__init__.py
zpp_args/args.py
zpp_args-1.3.4.dist-info/LICENSE
zpp_args-1.3.4.dist-info/METADATA
zpp_args-1.3.4.dist-info/WHEEL
zpp_args-1.3.4.dist-info/top_level.txt
zpp_args-1.3.4.dist-info/RECORD
