Metadata-Version: 2.1
Name: zpp_args
Version: 1.3.4
Summary: Module pour le traitement des arguments d'une ligne de commande
Home-page: https://github.com/ZephyrOff/zpp_args
Author: 
License: MIT License
Project-URL: Documentation, https://github.com/ZephyrOff/zpp_args
Keywords: terminal args zephyroff
Platform: ALL
Classifier: Development Status :: 5 - Production/Stable
Classifier: Environment :: Console
Classifier: License :: OSI Approved :: MIT License
Classifier: Programming Language :: Python :: 3
License-File: LICENSE
